aliyunsdkworkbench_inner/__init__.py
aliyunsdkworkbench_inner/request/__init__.py
aliyunsdkworkbench_inner/request/v20210121/InnerAddAppDeveloperRequest.py
aliyunsdkworkbench_inner/request/v20210121/InnerAddAppRequest.py
aliyunsdkworkbench_inner/request/v20210121/InnerAddEnvironmentRequest.py
aliyunsdkworkbench_inner/request/v20210121/InnerAddMainMemberRequest.py
aliyunsdkworkbench_inner/request/v20210121/InnerAddOrgMemberRequest.py
aliyunsdkworkbench_inner/request/v20210121/InnerAddProductRequest.py
aliyunsdkworkbench_inner/request/v20210121/InnerAddSolutionRequest.py
aliyunsdkworkbench_inner/request/v20210121/InnerCancelPartnerRequest.py
aliyunsdkworkbench_inner/request/v20210121/InnerDeleteAppRequest.py
aliyunsdkworkbench_inner/request/v20210121/InnerDeleteEnvironmentRequest.py
aliyunsdkworkbench_inner/request/v20210121/InnerDeleteSolutionRequest.py
aliyunsdkworkbench_inner/request/v20210121/InnerDeployAppRequest.py
aliyunsdkworkbench_inner/request/v20210121/InnerEditAppRequest.py
aliyunsdkworkbench_inner/request/v20210121/InnerEditEnvironmentRequest.py
aliyunsdkworkbench_inner/request/v20210121/InnerEditProductRequest.py
aliyunsdkworkbench_inner/request/v20210121/InnerEditSolutionRequest.py
aliyunsdkworkbench_inner/request/v20210121/InnerGetAppApiGatewayAppRequest.py
aliyunsdkworkbench_inner/request/v20210121/InnerGetAppApiGatewayGroupRequest.py
aliyunsdkworkbench_inner/request/v20210121/InnerGetAppApiGatewayRequest.py
aliyunsdkworkbench_inner/request/v20210121/InnerGetAppDeployDomainRequest.py
aliyunsdkworkbench_inner/request/v20210121/InnerGetAppDeployLogRequest.py
aliyunsdkworkbench_inner/request/v20210121/InnerGetAppDeployRequest.py
aliyunsdkworkbench_inner/request/v20210121/InnerGetAppEnvConfigRequest.py
aliyunsdkworkbench_inner/request/v20210121/InnerGetAppGlobalConfigRequest.py
aliyunsdkworkbench_inner/request/v20210121/InnerGetAppPackageUploadUrlRequest.py
aliyunsdkworkbench_inner/request/v20210121/InnerGetAppRepositoryRequest.py
aliyun_python_sdk_workbench_inner-2.0.3.dist-info/LICENSE
aliyun_python_sdk_workbench_inner-2.0.3.dist-info/METADATA
aliyun_python_sdk_workbench_inner-2.0.3.dist-info/WHEEL
aliyun_python_sdk_workbench_inner-2.0.3.dist-info/top_level.txt
aliyun_python_sdk_workbench_inner-2.0.3.dist-info/RECORD
